artificial_unintelligence/__init__.py
artificial_unintelligence/__main__.py
artificial_unintelligence/functions.py
artificial_unintelligence/word_bank.json
artificial_unintelligence-0.1.4.dist-info/licenses/LICENSE
artificial_unintelligence-0.1.4.dist-info/METADATA
artificial_unintelligence-0.1.4.dist-info/WHEEL
artificial_unintelligence-0.1.4.dist-info/entry_points.txt
artificial_unintelligence-0.1.4.dist-info/top_level.txt
artificial_unintelligence-0.1.4.dist-info/RECORD
