Metadata-Version: 2.4
Name: artificial-unintelligence
Version: 0.1.4
Summary: artifical unintelligence, a funny AI
Author-email: "Jonathan Gao, " <ruoyuanmai20030513@gmail.com>, Buki Seid <mds831@nyu.edu>, Jonathan <jg6911@nyu.edu>
License:                     GNU GENERAL PUBLIC LICENSE
Project-URL: Homepage, https://github.com/software-students-spring2025/3-python-package-zebrazooka/tree/main/artificial_unintelligence
Project-URL: Repository, https://github.com/software-students-spring2025/3-python-package-zebrazooka/tree/main/artificial_unintelligence.git
Project-URL: Bug Tracker, https://github.com/software-students-spring2025/3-python-package-zebrazooka/tree/main/artificial_unintelligence/issues
Keywords: python,fun,humor,random,artifical intelligence,AI
Classifier: Programming Language :: Python :: 3
Classifier: Intended Audience :: Developers
Classifier: License :: OSI Approved :: GNU General Public License v3 (GPLv3)
Classifier: Operating System :: OS Independent
Requires-Python: >=3.7
License-File: LICENSE
Provides-Extra: dev
Requires-Dist: pytest; extra == "dev"
Dynamic: license-file
